LICENSE
MANIFEST.in
README.md
setup.cfg
setup.py
carefree_drawboard.egg-info/PKG-INFO
carefree_drawboard.egg-info/SOURCES.txt
carefree_drawboard.egg-info/dependency_links.txt
carefree_drawboard.egg-info/entry_points.txt
carefree_drawboard.egg-info/requires.txt
carefree_drawboard.egg-info/top_level.txt
cfdraw/__init__.py
cfdraw/cli.py
cfdraw/config.py
cfdraw/constants.py
cfdraw/.web/.env
cfdraw/.web/.prettierrc
cfdraw/.web/index.html
cfdraw/.web/package.json
cfdraw/.web/tsconfig.json
cfdraw/.web/tsconfig.node.json
cfdraw/.web/tsconfig.paths.json
cfdraw/.web/vite.config.ts
cfdraw/.web/yarn.lock
cfdraw/.web/src/App.tsx
cfdraw/.web/src/_settings.ts
cfdraw/.web/src/env.d.ts
cfdraw/.web/src/index.scss
cfdraw/.web/src/index.tsx
cfdraw/.web/src/react-app-env.d.ts
cfdraw/.web/src/reset.d.ts
cfdraw/.web/src/vite-env.d.ts
cfdraw/.web/src/actions/addImage.ts
cfdraw/.web/src/actions/addText.ts
cfdraw/.web/src/actions/download.ts
cfdraw/.web/src/actions/export.ts
cfdraw/.web/src/actions/graphOps.ts
cfdraw/.web/src/actions/i18n.ts
cfdraw/.web/src/actions/importMeta.ts
cfdraw/.web/src/actions/managePlugins.ts
cfdraw/.web/src/actions/manageProjects.ts
cfdraw/.web/src/actions/update.ts
cfdraw/.web/src/actions/uploadImage.ts
cfdraw/.web/src/assets/image-placeholder.svg
cfdraw/.web/src/assets/nsfw-placeholder.svg
cfdraw/.web/src/assets/icons/add-blank.svg
cfdraw/.web/src/assets/icons/add-frame.svg
cfdraw/.web/src/assets/icons/add-image.svg
cfdraw/.web/src/assets/icons/add-noliFrame.svg
cfdraw/.web/src/assets/icons/add-noliTextFrame.svg
cfdraw/.web/src/assets/icons/add-project.svg
cfdraw/.web/src/assets/icons/add-text.svg
cfdraw/.web/src/assets/icons/add.svg
cfdraw/.web/src/assets/icons/arrange.svg
cfdraw/.web/src/assets/icons/arrow-down.svg
cfdraw/.web/src/assets/icons/brush.svg
cfdraw/.web/src/assets/icons/corner-radius.svg
cfdraw/.web/src/assets/icons/delete.svg
cfdraw/.web/src/assets/icons/download.svg
cfdraw/.web/src/assets/icons/editor.svg
cfdraw/.web/src/assets/icons/email.svg
cfdraw/.web/src/assets/icons/github.svg
cfdraw/.web/src/assets/icons/group-editor.svg
cfdraw/.web/src/assets/icons/image.svg
cfdraw/.web/src/assets/icons/import.svg
cfdraw/.web/src/assets/icons/meta.svg
cfdraw/.web/src/assets/icons/minus.svg
