Metadata-Version: 2.1
Name: carefree-drawboard
Version: 0.0.3a0
Summary: 🎨 Infinite Drawboard in Python
Author: carefree0910
Author-email: syameimaru.saki@gmail.com
Keywords: python carefree-learn drawboard
License-File: LICENSE
